Metadata-Version: 2.1
Name: adnmtf
Version: 0.1.159
Summary: Non-negative Matrix and Tensor Factorization
Home-page: https://github.com/Advestis/adnmtf
Author: Paul Fogel
Author-email: pfogel@advestis.com
License: MIT
Project-URL: Bug Tracker, https://github.com/Advestis/adnmtf/issues
Project-URL: Documentation, https://advestis.github.io/adnmtf
Project-URL: Source Code, https://github.com/Advestis/adnmtf/
Platform: UNKNOWN
Classifier: Development Status :: 5 - Production/Stable
Classifier: License :: OSI Approved :: MIT License
Classifier: Operating System :: Unix
Classifier: Operating System :: Microsoft :: Windows
Classifier: Programming Language :: Python :: 3.6
Classifier: Programming Language :: Python :: 3.7
Classifier: Programming Language :: Python :: 3.8
Classifier: Programming Language :: Python :: 3.9
Requires-Python: >=3.6
License-File: LICENSE
